{
    "# playlist settings": "播放列表设置 #",
    "playlist_path": "F:/music",
    "playlist": [
        [
            "歌手",
            [
                "Taylor Swift",
                "F:/music\\歌手\\Taylor Swift"
            ],
            [
                "李荣浩",
                "F:/music\\歌手\\李荣浩"
            ],
            [
                "林俊杰",
                "F:/music\\歌手\\林俊杰"
            ],
            [
                "薛之谦",
                "F:/music\\歌手\\薛之谦"
            ],
            [
                "周杰伦",
                "F:/music\\歌手\\周杰伦"
            ],
            [
                "最近删除",
                "F:/music\\歌手\\最近删除"
            ]
        ],
        [
            "自定义歌单",
            [
                "钢琴曲",
                "F:/music\\自定义歌单\\钢琴曲"
            ],
            [
                "铃声",
                "F:/music\\自定义歌单\\铃声"
            ],
            [
                "总库",
                "F:/music\\自定义歌单\\总库"
            ],
            [
                "最近删除",
                "F:/music\\自定义歌单\\最近删除"
            ],
            [
                "❤️",
                "F:/music\\自定义歌单\\❤️"
            ]
        ]
    ],
    "# Image/icon file path settings": "图片/图标文件路径设置 #",
    "ApplicationWindowBackGround": "d:\\LocalUsers\\Goodnameisfordoggy-Gitee\\a-simple-MusicPlayer\\phbimage\\Golden Buddha.png",
    "ApplicationWindowIcon": "d:\\LocalUsers\\Goodnameisfordoggy-Gitee\\a-simple-MusicPlayer\\phbimage\\player.png",
    "SearchUIBackGround": "d:\\LocalUsers\\Goodnameisfordoggy-Gitee\\a-simple-MusicPlayer\\phbimage\\Beauty With Headset.png",
    "SearchUIIcon": "d:\\LocalUsers\\Goodnameisfordoggy-Gitee\\a-simple-MusicPlayer\\phbimage\\Beauty With Headset.png",
    "# Run data while playing": "播放时运行数据 #",
    "current_songlist_path": "F:/music\\歌手\\Taylor Swift",
    "foregoing_songlist_path": "F:/music\\歌手\\Taylor Swift",
    "current_music_number": 76,
    "file_total_time": 245,
    "current_position": 139.60179615020752,
    "current_music_name": "How You Get The Girl(Karaoke Version)",
    "current_songlist_group": "歌手",
    "need_cycle": false,
    "# Shortcut Key Settings": "快捷键设置 #",
    "key_press_programme": "0",
    "use_custom_shortcut_keys": true,
    "custom_shortcut_keys": {
        "next_play": "按下快捷键",
        "previous_play": "按下快捷键",
        "pause_or_begin": "按下快捷键",
        "random_play": "按下快捷键",
        "single_cycle_play": "按下快捷键"
    },
    "# Other Settings": "其他设置 #",
    "audio_file_suffixes": [
        ".mp3",
        ".wav",
        ".ogg",
        ".flac"
    ],
    "opened_times": 42,
    "current_songlist": {
        "1": "F:/music\\歌手\\Taylor Swift\\22 (Taylor’s Version)--Taylor Swift.mp3",
        "2": "F:/music\\歌手\\Taylor Swift\\22 (Ultimix By Brian Roche)--Taylor Swift.mp3",
        "3": "F:/music\\歌手\\Taylor Swift\\22(kw inst)--Taylor Swift.mp3",
        "4": "F:/music\\歌手\\Taylor Swift\\22(Taylor’s Version)--Taylor Swift.mp3",
        "5": "F:/music\\歌手\\Taylor Swift\\A Place in this World--Taylor Swift.mp3",
        "6": "F:/music\\歌手\\Taylor Swift\\Afterglow--Taylor Swift.mp3",
        "7": "F:/music\\歌手\\Taylor Swift\\All Of The Girls You Loved Before--Taylor Swift.mp3",
        "8": "F:/music\\歌手\\Taylor Swift\\All Too Well (Sad Girl Autumn Version)- Recorded at Long Pond Studios--Taylor Swift.mp3",
        "9": "F:/music\\歌手\\Taylor Swift\\All Too Well (Taylor’s Version)--Taylor Swift.mp3",
        "10": "F:/music\\歌手\\Taylor Swift\\All Too Well (Ten Minute Version) (Taylor’s Version) (From The Vault)--Taylor Swift.mp3",
        "11": "F:/music\\歌手\\Taylor Swift\\All You Had To Do Was Stay--Taylor Swift.mp3",
        "12": "F:/music\\歌手\\Taylor Swift\\American Girl--Taylor Swift.mp3",
        "13": "F:/music\\歌手\\Taylor Swift\\Anti-Hero (Feat. Bleachers)--Taylor Swift&Bleachers.mp3",
        "14": "F:/music\\歌手\\Taylor Swift\\Anti-Hero(Acoustic Version)--Taylor Swift.mp3",
        "15": "F:/music\\歌手\\Taylor Swift\\Anti-Hero--Taylor Swift.mp3",
        "16": "F:/music\\歌手\\Taylor Swift\\august--Taylor Swift.mp3",
        "17": "F:/music\\歌手\\Taylor Swift\\Babe--Sugarland&Taylor Swift.mp3",
        "18": "F:/music\\歌手\\Taylor Swift\\Back To December(Live)--Taylor Swift.mp3",
        "19": "F:/music\\歌手\\Taylor Swift\\Back to December--Taylor Swift.mp3",
        "20": "F:/music\\歌手\\Taylor Swift\\Bad Blood(Instrumental With Background Vocals)--Taylor Swift.mp3",
        "21": "F:/music\\歌手\\Taylor Swift\\Bad Blood--Taylor Swift&Kendrick Lamar.mp3",
        "22": "F:/music\\歌手\\Taylor Swift\\Bad Blood--Taylor Swift.mp3",
        "23": "F:/music\\歌手\\Taylor Swift\\Beautiful Ghosts(From The Motion Picture Soundtrack ”Cats”)--Taylor Swift.mp3",
        "24": "F:/music\\歌手\\Taylor Swift\\Begin Again--Taylor Swift.mp3",
        "25": "F:/music\\歌手\\Taylor Swift\\Bejeweled--Taylor Swift.mp3",
        "26": "F:/music\\歌手\\Taylor Swift\\Better Than Revenge--Taylor Swift.mp3",
        "27": "F:/music\\歌手\\Taylor Swift\\betty(Explicit)--Taylor Swift.mp3",
        "28": "F:/music\\歌手\\Taylor Swift\\Bigger Than The Whole Sky--Taylor Swift.mp3",
        "29": "F:/music\\歌手\\Taylor Swift\\Blank Space (2014维多利亚的秘密现场)--Taylor Swift.mp3",
        "30": "F:/music\\歌手\\Taylor Swift\\Blank Space--Taylor Swift.mp3",
        "31": "F:/music\\歌手\\Taylor Swift\\Breathe--Taylor Swift&Colbie Caillat.mp3",
        "32": "F:/music\\歌手\\Taylor Swift\\Call It What You Want--Taylor Swift.mp3",
        "33": "F:/music\\歌手\\Taylor Swift\\cardigan(cabin in candlelight version)--Taylor Swift.mp3",
        "34": "F:/music\\歌手\\Taylor Swift\\cardigan--Taylor Swift.mp3",
        "35": "F:/music\\歌手\\Taylor Swift\\Carolina(From The Motion Picture “Where The Crawdads Sing”)--Taylor Swift.mp3",
        "36": "F:/music\\歌手\\Taylor Swift\\champagne problems(Explicit)--Taylor Swift.mp3",
        "37": "F:/music\\歌手\\Taylor Swift\\Christmas Tree Farm--Taylor Swift.mp3",
        "38": "F:/music\\歌手\\Taylor Swift\\Clean--Taylor Swift.mp3",
        "39": "F:/music\\歌手\\Taylor Swift\\Cornelia Street--Taylor Swift.mp3",
        "40": "F:/music\\歌手\\Taylor Swift\\cowboy like me(Explicit)--Taylor Swift.mp3",
        "41": "F:/music\\歌手\\Taylor Swift\\Crazier--Taylor Swift.mp3",
        "42": "F:/music\\歌手\\Taylor Swift\\Cruel Summer(Live)--Taylor Swift.mp3",
        "43": "F:/music\\歌手\\Taylor Swift\\Cruel Summer--Taylor Swift.mp3",
        "44": "F:/music\\歌手\\Taylor Swift\\Dancing With Our Hands Tied--Taylor Swift.mp3",
        "45": "F:/music\\歌手\\Taylor Swift\\Daylight(Live From Paris)--Taylor Swift.mp3",
        "46": "F:/music\\歌手\\Taylor Swift\\Daylight--Taylor Swift.mp3",
        "47": "F:/music\\歌手\\Taylor Swift\\Dear Reader--Taylor Swift.mp3",
        "48": "F:/music\\歌手\\Taylor Swift\\Death By A Thousand Cuts--Taylor Swift.mp3",
        "49": "F:/music\\歌手\\Taylor Swift\\Delicate(Karaoke Version)--Taylor Swift.mp3",
        "50": "F:/music\\歌手\\Taylor Swift\\Delicate(Seeb Remix)--Taylor Swift&SeeB.mp3",
        "51": "F:/music\\歌手\\Taylor Swift\\Delicate--Taylor Swift.mp3",
        "52": "F:/music\\歌手\\Taylor Swift\\Don’t Blame Me--Taylor Swift.mp3",
        "53": "F:/music\\歌手\\Taylor Swift\\dorothea--Taylor Swift.mp3",
        "54": "F:/music\\歌手\\Taylor Swift\\Dress--Taylor Swift.mp3",
        "55": "F:/music\\歌手\\Taylor Swift\\Drive All Night--Taylor Swift.mp3",
        "56": "F:/music\\歌手\\Taylor Swift\\Enchanted--Taylor Swift.mp3",
        "57": "F:/music\\歌手\\Taylor Swift\\End Game--Taylor Swift&Ed Sheeran&Future.mp3",
        "58": "F:/music\\歌手\\Taylor Swift\\epiphany--Taylor Swift.mp3",
        "59": "F:/music\\歌手\\Taylor Swift\\evermore--Taylor Swift&Bon Iver.mp3",
        "60": "F:/music\\歌手\\Taylor Swift\\exile--Taylor Swift&Bon Iver.mp3",
        "61": "F:/music\\歌手\\Taylor Swift\\Eyes Open (Taylor’s Version)--Taylor Swift.mp3",
        "62": "F:/music\\歌手\\Taylor Swift\\False God--Taylor Swift.mp3",
        "63": "F:/music\\歌手\\Taylor Swift\\Fearless(Demo)--Taylor Swift.mp3",
        "64": "F:/music\\歌手\\Taylor Swift\\Fearless--Taylor Swift.mp3",
        "65": "F:/music\\歌手\\Taylor Swift\\Getaway Car--Taylor Swift.mp3",
        "66": "F:/music\\歌手\\Taylor Swift\\gold rush(Explicit)--Taylor Swift.mp3",
        "67": "F:/music\\歌手\\Taylor Swift\\Gorgeous (Karaoke Version)--Taylor Swift.mp3",
        "68": "F:/music\\歌手\\Taylor Swift\\Gorgeous--Taylor Swift.mp3",
        "69": "F:/music\\歌手\\Taylor Swift\\Hey Stephen(Live)--Taylor Swift.mp3",
        "70": "F:/music\\歌手\\Taylor Swift\\High Infidelity--Taylor Swift.mp3",
        "71": "F:/music\\歌手\\Taylor Swift\\Highway Don’t Care(feat. Taylor Swift & Keith Urban)--Tim McGraw&Keith Urban&Taylor Swift.mp3",
        "72": "F:/music\\歌手\\Taylor Swift\\Highway Don’t Care--Tim McGraw&Taylor Swift&Keith Urban.mp3",
        "73": "F:/music\\歌手\\Taylor Swift\\Highway Don’t Care--Tim McGraw&Taylor Swift.mp3",
        "74": "F:/music\\歌手\\Taylor Swift\\Hits Different(Clean)--Taylor Swift.mp3",
        "75": "F:/music\\歌手\\Taylor Swift\\Hits Different(Explicit)--Taylor Swift.mp3",
        "76": "F:/music\\歌手\\Taylor Swift\\How You Get The Girl(Karaoke Version)--Taylor Swift.mp3",
        "77": "F:/music\\歌手\\Taylor Swift\\How You Get The Girl--Taylor Swift.mp3",
        "78": "F:/music\\歌手\\Taylor Swift\\I Did Something Bad --Taylor Swift.mp3",
        "79": "F:/music\\歌手\\Taylor Swift\\I Don’t Wanna Live Forever(Fifty Shades Darker)--ZAYN&Taylor Swift.mp3",
        "80": "F:/music\\歌手\\Taylor Swift\\I Forgot That You Existed--Taylor Swift.mp3",
        "81": "F:/music\\歌手\\Taylor Swift\\I Knew You Were Trouble (Taylor’s Version)--Taylor Swift.mp3",
        "82": "F:/music\\歌手\\Taylor Swift\\I Knew You Were Trouble [2012]--Taylor Swift.mp3",
        "83": "F:/music\\歌手\\Taylor Swift\\I Knew You Were Trouble(Fish Fugue Remix)--Taylor Swift.mp3",
        "84": "F:/music\\歌手\\Taylor Swift\\I Knew You Were Trouble(Taylor’s Version)--Taylor Swift.mp3",
        "85": "F:/music\\歌手\\Taylor Swift\\I Knew You Were Trouble--Taylor Swift.mp3",
        "86": "F:/music\\歌手\\Taylor Swift\\I Knew You Were Trouble.--Taylor Swift.mp3",
        "87": "F:/music\\歌手\\Taylor Swift\\I Know Places--Taylor Swift.mp3",
        "88": "F:/music\\歌手\\Taylor Swift\\I Think He Knows--Taylor Swift.mp3",
        "89": "F:/music\\歌手\\Taylor Swift\\If This Was A Movie(Taylor’s Version)--Taylor Swift.mp3",
        "90": "F:/music\\歌手\\Taylor Swift\\If This Was A Movie--Taylor Swift.mp3",
        "91": "F:/music\\歌手\\Taylor Swift\\invisible string--Taylor Swift.mp3",
        "92": "F:/music\\歌手\\Taylor Swift\\Invisible--Taylor Swift.mp3",
        "93": "F:/music\\歌手\\Taylor Swift\\It’s Nice To Have A Friend--Taylor Swift.mp3",
        "94": "F:/music\\歌手\\Taylor Swift\\Jump Then Fall--Taylor Swift.mp3",
        "95": "F:/music\\歌手\\Taylor Swift\\Karma(Clean)--Taylor Swift&Ice Spice.mp3",
        "96": "F:/music\\歌手\\Taylor Swift\\Karma(Clean)--Taylor Swift.mp3",
        "97": "F:/music\\歌手\\Taylor Swift\\Karma(Explicit)--Taylor Swift&Ice Spice.mp3",
        "98": "F:/music\\歌手\\Taylor Swift\\Karma(Explicit)--Taylor Swift.mp3",
        "99": "F:/music\\歌手\\Taylor Swift\\King of My Heart--Taylor Swift.mp3",
        "100": "F:/music\\歌手\\Taylor Swift\\Labyrinth--Taylor Swift.mp3",
        "101": "F:/music\\歌手\\Taylor Swift\\Last Christmas--Taylor Swift.mp3",
        "102": "F:/music\\歌手\\Taylor Swift\\Last Kiss(Live)--Taylor Swift.mp3",
        "103": "F:/music\\歌手\\Taylor Swift\\Lavender Haze(Acoustic Version)--Taylor Swift.mp3",
        "104": "F:/music\\歌手\\Taylor Swift\\Lavender Haze(Explicit)--Taylor Swift.mp3",
        "105": "F:/music\\歌手\\Taylor Swift\\London Boy--Taylor Swift.mp3",
        "106": "F:/music\\歌手\\Taylor Swift\\Long Live--Taylor Swift&Paula Fernandes.mp3",
        "107": "F:/music\\歌手\\Taylor Swift\\long story short--Taylor Swift.mp3",
        "108": "F:/music\\歌手\\Taylor Swift\\Look What You Made Me Do(Karaoke Version)--Taylor Swift.mp3",
        "109": "F:/music\\歌手\\Taylor Swift\\Look What You Made Me Do--Taylor Swift.mp3",
        "110": "F:/music\\歌手\\Taylor Swift\\Love Story (Made Famous by Taylor Swift ) - Symphonic Version--Taylor Swift&St. Martin’s Symphony Of Los Angeles&Adam Hamilton.mp3",
        "111": "F:/music\\歌手\\Taylor Swift\\Love Story--Taylor Swift.mp3",
        "112": "F:/music\\歌手\\Taylor Swift\\Lover(First Dance Remix)--Taylor Swift.mp3",
        "113": "F:/music\\歌手\\Taylor Swift\\Lover(Live From Paris)--Taylor Swift.mp3",
        "114": "F:/music\\歌手\\Taylor Swift\\Lover--Taylor Swift.mp3",
        "115": "F:/music\\歌手\\Taylor Swift\\mad woman(Explicit)--Taylor Swift.mp3",
        "116": "F:/music\\歌手\\Taylor Swift\\marjorie--Taylor Swift.mp3",
        "117": "F:/music\\歌手\\Taylor Swift\\Maroon(Clean)--Taylor Swift.mp3",
        "118": "F:/music\\歌手\\Taylor Swift\\Maroon(Explicit)--Taylor Swift.mp3",
        "119": "F:/music\\歌手\\Taylor Swift\\Mastermind--Taylor Swift.mp3",
        "120": "F:/music\\歌手\\Taylor Swift\\ME!(Feat. Brendon Urie Of Panic! At The Disco)--Taylor Swift&Brendon Urie.mp3",
        "121": "F:/music\\歌手\\Taylor Swift\\ME!(Live From Paris)--Taylor Swift.mp3",
        "122": "F:/music\\歌手\\Taylor Swift\\Mean--Taylor Swift.mp3",
        "123": "F:/music\\歌手\\Taylor Swift\\Midnight Rain--Taylor Swift.mp3",
        "124": "F:/music\\歌手\\Taylor Swift\\Mine(POP Mix)--Taylor Swift.mp3",
        "125": "F:/music\\歌手\\Taylor Swift\\Mine--Taylor Swift.mp3",
        "126": "F:/music\\歌手\\Taylor Swift\\mirrorball--Taylor Swift.mp3",
        "127": "F:/music\\歌手\\Taylor Swift\\Miss Americana & The Heartbreak Prince--Taylor Swift.mp3",
        "128": "F:/music\\歌手\\Taylor Swift\\Mr. Perfectly Fine(Taylor’s Version)--Taylor Swift.mp3",
        "129": "F:/music\\歌手\\Taylor Swift\\My Songs Know What You Did In the Dark--Taylor Swift&Fall Out Boy.mp3",
        "130": "F:/music\\歌手\\Taylor Swift\\my tears ricochet--Taylor Swift.mp3",
        "131": "F:/music\\歌手\\Taylor Swift\\New Romantics--Taylor Swift.mp3",
        "132": "F:/music\\歌手\\Taylor Swift\\New Year’s Day--Taylor Swift.mp3",
        "133": "F:/music\\歌手\\Taylor Swift\\no body， no crime--Taylor Swift&Haim.mp3",
        "134": "F:/music\\歌手\\Taylor Swift\\Only The Young(Featured in Miss Americana)--Taylor Swift.mp3",
        "135": "F:/music\\歌手\\Taylor Swift\\Our Song (Radio Single Version)--Taylor Swift.mp3",
        "136": "F:/music\\歌手\\Taylor Swift\\Our Song(US Album Version)--Taylor Swift.mp3",
        "137": "F:/music\\歌手\\Taylor Swift\\Ours--Taylor Swift.mp3",
        "138": "F:/music\\歌手\\Taylor Swift\\Out Of The Woods--Taylor Swift.mp3",
        "139": "F:/music\\歌手\\Taylor Swift\\Paper Rings--Taylor Swift.mp3",
        "140": "F:/music\\歌手\\Taylor Swift\\Paris--Taylor Swift.mp3",
        "141": "F:/music\\歌手\\Taylor Swift\\Red (Taylor’s Version)--Taylor Swift.mp3",
        "142": "F:/music\\歌手\\Taylor Swift\\Red--Taylor Swift.mp3",
        "143": "F:/music\\歌手\\Taylor Swift\\Safe & Sound (Taylor’s Version)--Taylor Swift&Joy Williams&John Paul White.mp3",
        "144": "F:/music\\歌手\\Taylor Swift\\Safe & Sound(from The Hunger Games Soundtrack)--Taylor Swift&The Civil Wars.mp3",
        "145": "F:/music\\歌手\\Taylor Swift\\Safe And Sound--Taylor Swift.mp3",
        "146": "F:/music\\歌手\\Taylor Swift\\See You Again (片段)--Taylor Swift.mp3",
        "147": "F:/music\\歌手\\Taylor Swift\\seven--Taylor Swift.mp3",
        "148": "F:/music\\歌手\\Taylor Swift\\Shake It Off--Taylor Swift.mp3",
        "149": "F:/music\\歌手\\Taylor Swift\\Snow On The Beach(Clean)--Taylor Swift&Lana Del Rey.mp3",
        "150": "F:/music\\歌手\\Taylor Swift\\Snow On The Beach(Explicit)--Taylor Swift&Lana Del Rey.mp3",
        "151": "F:/music\\歌手\\Taylor Swift\\So It Goes...--Taylor Swift.mp3",
        "152": "F:/music\\歌手\\Taylor Swift\\Soon You’ll Get Better (feat. Dixie Chicks)--Taylor Swift.mp3",
        "153": "F:/music\\歌手\\Taylor Swift\\Sparks Fly(Live 2011)--Taylor Swift.mp3",
        "154": "F:/music\\歌手\\Taylor Swift\\Sparks Fly--Taylor Swift.mp3",
        "155": "F:/music\\歌手\\Taylor Swift\\Speak Now--Taylor Swift.mp3",
        "156": "F:/music\\歌手\\Taylor Swift\\Starlight--Taylor Swift.mp3",
        "157": "F:/music\\歌手\\Taylor Swift\\Stay Stay Stay--Taylor Swift.mp3",
        "158": "F:/music\\歌手\\Taylor Swift\\Style (2014维多利亚的秘密现场)--Taylor Swift.mp3",
        "159": "F:/music\\歌手\\Taylor Swift\\Style(Karaoke Version)--Taylor Swift.mp3",
        "160": "F:/music\\歌手\\Taylor Swift\\Style--Taylor Swift.mp3",
        "161": "F:/music\\歌手\\Taylor Swift\\Sweet Nothing--Taylor Swift.mp3",
        "162": "F:/music\\歌手\\Taylor Swift\\Taylor Swift(Explicit)--Yung Tomorrow.mp3",
        "163": "F:/music\\歌手\\Taylor Swift\\Taylor Swift(Fifteen 现场版)--Taylor Swift.mp3",
        "164": "F:/music\\歌手\\Taylor Swift\\Taylor Swift(Welcome To New York #taylor霉霉 #1989 #黑胶)--泰勒甜本甜X.mp3",
        "165": "F:/music\\歌手\\Taylor Swift\\Teardrops On My Guitar(Acoustic)--Taylor Swift.mp3",
        "166": "F:/music\\歌手\\Taylor Swift\\Tell Me--Taylor Swift.mp3",
        "167": "F:/music\\歌手\\Taylor Swift\\the 1(Explicit)--Taylor Swift.mp3",
        "168": "F:/music\\歌手\\Taylor Swift\\The Archer--Taylor Swift.mp3",
        "169": "F:/music\\歌手\\Taylor Swift\\The Great War--Taylor Swift.mp3",
        "170": "F:/music\\歌手\\Taylor Swift\\The Joker And The Queen (feat. Taylor Swift)--Ed Sheeran&Taylor Swift.mp3",
        "171": "F:/music\\歌手\\Taylor Swift\\the lakes(original version)--Taylor Swift.mp3",
        "172": "F:/music\\歌手\\Taylor Swift\\the lakes--Taylor Swift.mp3",
        "173": "F:/music\\歌手\\Taylor Swift\\the last great american dynasty(Explicit)--Taylor Swift.mp3",
        "174": "F:/music\\歌手\\Taylor Swift\\The Man(Live From Paris)--Taylor Swift.mp3",
        "175": "F:/music\\歌手\\Taylor Swift\\The Man--Taylor Swift.mp3",
        "176": "F:/music\\歌手\\Taylor Swift\\this is me trying(the long pond studio sessions)--Taylor Swift.mp3",
        "177": "F:/music\\歌手\\Taylor Swift\\This Love(Taylor’s Version)--Taylor Swift.mp3",
        "178": "F:/music\\歌手\\Taylor Swift\\This Love--Taylor Swift.mp3",
        "179": "F:/music\\歌手\\Taylor Swift\\Tim McGraw--Taylor Swift.mp3",
        "180": "F:/music\\歌手\\Taylor Swift\\tolerate it(Explicit)--Taylor Swift.mp3",
        "181": "F:/music\\歌手\\Taylor Swift\\Two Is Better Than One--Boys Like Girls&Taylor Swift.mp3",
        "182": "F:/music\\歌手\\Taylor Swift\\Untouchable--Taylor Swift.mp3",
        "183": "F:/music\\歌手\\Taylor Swift\\Vigilante Shit(Clean)--Taylor Swift.mp3",
        "184": "F:/music\\歌手\\Taylor Swift\\Vigilante Shit(Explicit)--Taylor Swift.mp3",
        "185": "F:/music\\歌手\\Taylor Swift\\We Are Never Ever Getting Back Together(Taylor’s Version)--Taylor Swift.mp3",
        "186": "F:/music\\歌手\\Taylor Swift\\We Are Never Ever Getting Back Together--Taylor Swift.mp3",
        "187": "F:/music\\歌手\\Taylor Swift\\Welcome To New York(Karaoke Version)--Taylor Swift.mp3",
        "188": "F:/music\\歌手\\Taylor Swift\\Welcome To New York(Tribute version originally performed by Taylor Swift)--Taylor Swift.mp3",
        "189": "F:/music\\歌手\\Taylor Swift\\Welcome To New York--Taylor Swift.mp3",
        "190": "F:/music\\歌手\\Taylor Swift\\Wildest Dream--Taylor Swift.mp3",
        "191": "F:/music\\歌手\\Taylor Swift\\Wildest Dreams(Karaoke Version)--Taylor Swift.mp3",
        "192": "F:/music\\歌手\\Taylor Swift\\Wildest Dreams(Taylor’s Version)--Taylor Swift.mp3",
        "193": "F:/music\\歌手\\Taylor Swift\\Wildest Dreams--Taylor Swift.mp3",
        "194": "F:/music\\歌手\\Taylor Swift\\willow(90’s trend remix)--Taylor Swift.mp3",
        "195": "F:/music\\歌手\\Taylor Swift\\willow(lonely witch version)--Taylor Swift.mp3",
        "196": "F:/music\\歌手\\Taylor Swift\\willow--Taylor Swift.mp3",
        "197": "F:/music\\歌手\\Taylor Swift\\Wonderland(Karaoke Version)--Taylor Swift.mp3",
        "198": "F:/music\\歌手\\Taylor Swift\\Wonderland--Taylor Swift.mp3",
        "199": "F:/music\\歌手\\Taylor Swift\\Would’ve， Could’ve， Should’ve--Taylor Swift.mp3",
        "200": "F:/music\\歌手\\Taylor Swift\\You All Over Me(Taylor’s Version)--Taylor Swift&Maren Morris.mp3",
        "201": "F:/music\\歌手\\Taylor Swift\\You Are In Love--Taylor Swift.mp3",
        "202": "F:/music\\歌手\\Taylor Swift\\You Belong With Me (Taylor’s Version)--Taylor Swift.mp3",
        "203": "F:/music\\歌手\\Taylor Swift\\You Belong With Me--Taylor Swift.mp3",
        "204": "F:/music\\歌手\\Taylor Swift\\You Need To Calm Down(Clean Bandit Remix)--Taylor Swift.mp3",
        "205": "F:/music\\歌手\\Taylor Swift\\You Need To Calm Down--Taylor Swift.mp3",
        "206": "F:/music\\歌手\\Taylor Swift\\You’re Not Sorry(CSI Remix)--Taylor Swift.mp3",
        "207": "F:/music\\歌手\\Taylor Swift\\You’re Not Sorry--Taylor Swift.mp3",
        "208": "F:/music\\歌手\\Taylor Swift\\You’re On Your Own， Kid--Taylor Swift.mp3",
        "209": "F:/music\\歌手\\Taylor Swift\\‘tis the damn season--Taylor Swift.mp3"
    }
}